W_Env/W_Env.py
W_Env/__init__.py
W_Env/task_Goal_Action.py
W_Env/task_Horizon.py
W_Env/task_Temporal_Discounting.py
W_Env/task_TwoStep.py
W_Env/task_TwoStep_Confidence.py
W_Env_CognitiveTasks-0.0.0.dist-info/METADATA
W_Env_CognitiveTasks-0.0.0.dist-info/WHEEL
W_Env_CognitiveTasks-0.0.0.dist-info/top_level.txt
W_Env_CognitiveTasks-0.0.0.dist-info/RECORD
