Metadata-Version: 2.1
Name: W-Env-CognitiveTasks
Version: 0.0.0
Summary: siyus environments
Author: Siyu Wang
Author-email: wangxsiyu@gmail.com
